funrec/__init__.py
funrec/utils.py
funrec/callbacks/__init__.py
funrec/callbacks/checkpoint.py
funrec/inputs/__init__.py
funrec/inputs/core.py
funrec/layers/__init__.py
funrec/layers/activation.py
funrec/layers/core.py
funrec/layers/interaction.py
funrec/layers/sequence.py
funrec/layers/utils.py
funrec/models/__init__.py
funrec/models/afm.py
funrec/models/afn.py
funrec/models/autoint.py
funrec/models/ccpm.py
funrec/models/dcn.py
funrec/models/dcnmix.py
funrec/models/deepfm.py
funrec/models/dien.py
funrec/models/difm.py
funrec/models/din.py
funrec/models/fibinet.py
funrec/models/ifm.py
funrec/models/mlr.py
funrec/models/nfm.py
funrec/models/onn.py
funrec/models/pnn.py
funrec/models/wdl.py
funrec/models/xdeepfm.py
funrec/models/base/__init__.py
funrec/models/base/base.py
funrec/models/base/line.py
funrec/models/multitask/__init__.py
funrec/models/multitask/esmm.py
funrec/models/multitask/mmoe.py
funrec/models/multitask/ple.py
funrec/models/multitask/sharedbottom.py
funrec-0.0.5.dist-info/METADATA
funrec-0.0.5.dist-info/WHEEL
funrec-0.0.5.dist-info/top_level.txt
funrec-0.0.5.dist-info/RECORD
