Metadata-Version: 2.4
Name: funrec
Version: 0.0.5
Summary: funrec
Author-email: 牛哥 <niuliangtao@qq.com>, farfarfun <farfarfun@qq.com>
Maintainer-email: 牛哥 <niuliangtao@qq.com>, farfarfun <farfarfun@qq.com>
Project-URL: Organization, https://github.com/farfarfun
Project-URL: Repository, https://github.com/farfarfun/funrec
Project-URL: Releases, https://github.com/farfarfun/funrec/releases
Requires-Python: >=3.9
Requires-Dist: funutil>=1.0.53
Requires-Dist: scikit-learn>=1.6.0
Requires-Dist: torch>=2.5.0
Requires-Dist: tqdm>=4.67.0
